sim_explorer/__init__.py
sim_explorer/assertion.py
sim_explorer/case.py
sim_explorer/exceptions.py
sim_explorer/json5.py
sim_explorer/models.py
sim_explorer/py.typed
sim_explorer/system_interface.py
sim_explorer/system_interface_osp.py
sim_explorer/cli/__init__.py
sim_explorer/cli/__main__.py
sim_explorer/cli/display_results.py
sim_explorer/utils/__init__.py
sim_explorer/utils/logging.py
sim_explorer/utils/misc.py
sim_explorer/utils/osp.py
sim_explorer/utils/paths.py
sim_explorer/utils/types.py
sim_explorer-0.2.1.dist-info/METADATA
sim_explorer-0.2.1.dist-info/WHEEL
sim_explorer-0.2.1.dist-info/entry_points.txt
sim_explorer-0.2.1.dist-info/licenses/LICENSE
sim_explorer-0.2.1.dist-info/RECORD
