Metadata-Version: 2.4
Name: sim-explorer
Version: 0.2.1
Summary: Experimentation tools on top of OSP simulation models.
Project-URL: Homepage, https://github.com/dnv-opensource/sim-explorer
Project-URL: Documentation, https://dnv-opensource.github.io/sim-explorer/README.html
Project-URL: Repository, https://github.com/dnv-opensource/sim-explorer.git
Project-URL: Issues, https://github.com/dnv-opensource/sim-explorer/issues
Project-URL: Changelog, https://github.com/dnv-opensource/sim-explorer/blob/main/CHANGELOG.md
Author-email: Siegfried Eisinger <Siegfried.Eisinger@dnv.com>
License: MIT License
License-File: LICENSE
Keywords: FMI,OSP,model,simulation
Classifier: Development Status :: 4 - Beta
Classifier: Environment :: Console
Classifier: Intended Audience :: Developers
Classifier: Intended Audience :: Science/Research
Classifier: License :: OSI Approved :: MIT License
Classifier: Operating System :: MacOS
Classifier: Operating System :: Microsoft :: Windows
Classifier: Operating System :: POSIX :: Linux
Classifier: Programming Language :: Python :: 3.10
Classifier: Programming Language :: Python :: 3.11
Classifier: Programming Language :: Python :: 3.12
Classifier: Topic :: Scientific/Engineering
Classifier: Topic :: Software Development :: Libraries :: Python Modules
Requires-Python: <3.13,>=3.10
Requires-Dist: component-model>=0.1.0
Requires-Dist: fmpy>=0.3.21
Requires-Dist: jsonpath-ng>=1.7.0
Requires-Dist: libcosimpy==0.0.2
Requires-Dist: matplotlib>=3.10
Requires-Dist: numpy>=1.26; python_version < '3.13'
Requires-Dist: numpy>=2.2; python_version >= '3.13'
Requires-Dist: pint>=0.24
Requires-Dist: plotly>=5.24
Requires-Dist: pydantic>=2.10.3
Requires-Dist: rich>=13.9.4
Requires-Dist: sympy>=1.13
Provides-Extra: editor
Requires-Dist: thonny>=4.1; extra == 'editor'
Provides-Extra: modeltest
Requires-Dist: fmpy>=0.3.21; extra == 'modeltest'
Provides-Extra: rest
Requires-Dist: docutils>=0.21; extra == 'rest'
